csv_health/__init__.py
csv_health/api.py
csv_health/audit.py
csv_health/cli.py
csv_health/logging_utils.py
csv_health/reconnecting.py
csv_health/state.py
csv_health-0.5.0.dist-info/licenses/LICENSE
csv_health-0.5.0.dist-info/METADATA
csv_health-0.5.0.dist-info/WHEEL
csv_health-0.5.0.dist-info/entry_points.txt
csv_health-0.5.0.dist-info/top_level.txt
csv_health-0.5.0.dist-info/RECORD
