Metadata-Version: 2.4
Name: csv-health
Version: 0.5.0
Summary: Confident CSV health checks: audit + state + processing, stored inside the active venv
Author-email: Your Name <you@example.com>
License: MIT License
Classifier: Programming Language :: Python :: 3
Classifier: License :: OSI Approved :: MIT License
Classifier: Operating System :: OS Independent
Classifier: Topic :: Software Development :: Libraries :: Python Modules
Requires-Python: >=3.9
License-File: LICENSE
Requires-Dist: pandas>=2.0
Dynamic: license-file
